client/__init__.py
client/client.py
server/__init__.py
server/server.py
tcp_client_server_raidix-0.0.1.dist-info/METADATA
tcp_client_server_raidix-0.0.1.dist-info/WHEEL
tcp_client_server_raidix-0.0.1.dist-info/top_level.txt
tcp_client_server_raidix-0.0.1.dist-info/RECORD
